tomputils/__init__.py
tomputils/util.py
tomputils/configupdater/__init__.py
tomputils/configupdater/configupdater_console.py
tomputils/downloader/__init__.py
tomputils/downloader/downloader.py
tomputils/downloader/downloader_console.py
tomputils/downloader/limit.py
tomputils/mattermost/__init__.py
tomputils/mattermost/mattermost.py
tomputils/mattermost/mattermost_console.py
tomputils/message/__init__.py
tomputils/message/emit_alarm.py
tomputils/message/messsagelogger/__init__.py
tomputils/message/messsagelogger/__main__.py
tomputils/message/messsagelogger/listener.py
tomputils/message/messsagelogger/shipper.py
tomputils/message/type/__init__.py
tomputils/message/type/alarm_pb2.py
tomputils/volcviewpublisher/__init__.py
tomputils-1.12.18.data/scripts/singleTimeout.sh
tomputils-1.12.18.dist-info/LICENSE
tomputils-1.12.18.dist-info/METADATA
tomputils-1.12.18.dist-info/WHEEL
tomputils-1.12.18.dist-info/dependency_links.txt
tomputils-1.12.18.dist-info/entry_points.txt
tomputils-1.12.18.dist-info/top_level.txt
tomputils-1.12.18.dist-info/RECORD
