Metadata-Version: 2.1
Name: tomputils
Version: 1.12.18
Summary: tomputils -- Supporting modules.
Home-page: http://github.com/tparker-usgs/tomputils
Author: Tom Parker
Author-email: tparker@usgs.gov
License: CC0
Keywords: mattermost
Platform: UNKNOWN
Classifier: Development Status :: 4 - Beta
Classifier: Topic :: Software Development :: Libraries
Classifier: License :: CC0 1.0 Universal (CC0 1.0) Public Domain Dedication
Requires-Dist: requests
Requires-Dist: future
Requires-Dist: pika
Requires-Dist: pycurl
Requires-Dist: pyOpenSSL
Requires-Dist: buffering-smtp-handler
Requires-Dist: svn
Requires-Dist: ruamel.yaml
